SCMG/__init__.py
SCMG/_version.py
SCMG/config/__init__.py
SCMG/config/modelparameters.py
SCMG/config/varables.py
SCMG/models/__init__.py
SCMG/models/GPT/__init__.py
SCMG/models/GPT/model.py
SCMG/models/GPT/sampler.py
SCMG/models/GPT2/__init__.py
SCMG/models/GPT2/model.py
SCMG/models/GPT2/sampler.py
SCMG/models/LSTM/__init__.py
SCMG/models/LSTM/model.py
SCMG/models/LSTM/sampler.py
SCMG/models/LSTM/trainer.py
SCMG/models/Reinvent/__init__.py
SCMG/models/Reinvent/model copy 2.py
SCMG/models/Reinvent/model copy.py
SCMG/models/Reinvent/model.py
SCMG/models/Reinvent/sampler.py
SCMG/models/Reinvent_Scaffold_Decorator/__init__.py
SCMG/models/Reinvent_Scaffold_Decorator/model copy 2.py
SCMG/models/Reinvent_Scaffold_Decorator/model copy.py
SCMG/models/Reinvent_Scaffold_Decorator/model.py
SCMG/models/Reinvent_Scaffold_Decorator/sampler.py
SCMG/models/Transformer/__init__.py
SCMG/models/Transformer/model copy 2.py
SCMG/models/Transformer/model copy 3.py
SCMG/models/Transformer/model copy.py
SCMG/models/Transformer/model.py
SCMG/models/Transformer/sampler.py
SCMG/models/Transformer_Test/__init__.py
SCMG/models/Transformer_Test/model.py
SCMG/models/Transformer_Test/sampler.py
SCMG/models/Transformer_Torch/__init__.py
SCMG/models/Transformer_Torch/model.py
SCMG/models/Transformer_Torch/sampler.py
SCMG/models/Transformer_debug/__init__.py
SCMG/models/Transformer_debug/model copy 2.py
SCMG/models/Transformer_debug/model copy.py
SCMG/models/Transformer_debug/model.py
SCMG/models/Transformer_debug/sampler.py
SCMG/models/Transformer_debug copy/__init__.py
SCMG/models/Transformer_debug copy/model copy 2.py
SCMG/models/Transformer_debug2/__init__.py
SCMG/models/Transformer_debug2/model copy 2.py
SCMG/models/Transformer_debug2/model copy.py
SCMG/models/Transformer_debug2/model.py
SCMG/models/Transformer_debug2/sampler.py
SCMG/models/Transformer_debug2 copy/__init__.py
SCMG/models/Transformer_debug2 copy/model copy 2.py
SCMG/models/Transformer_debug2 copy/model copy.py
scmg_toolkit-0.1.8.dist-info/licenses/LICENSE
scmg_toolkit-0.1.8.dist-info/METADATA
scmg_toolkit-0.1.8.dist-info/WHEEL
scmg_toolkit-0.1.8.dist-info/top_level.txt
scmg_toolkit-0.1.8.dist-info/RECORD
