Metadata-Version: 2.4
Name: scmg_toolkit
Version: 0.1.8
Summary: SCMG toolkit
License-Expression: MIT
Requires-Python: >=3.8
License-File: LICENSE
Requires-Dist: rdkit
Requires-Dist: SmilesPE
Requires-Dist: torch
Requires-Dist: torchvision
Dynamic: license-file
